odoo/addons/stock_warehouse_flow_delivery_refresh/README.rst
odoo/addons/stock_warehouse_flow_delivery_refresh/__init__.py
odoo/addons/stock_warehouse_flow_delivery_refresh/__manifest__.py
odoo/addons/stock_warehouse_flow_delivery_refresh/i18n/it.po
odoo/addons/stock_warehouse_flow_delivery_refresh/i18n/stock_warehouse_flow_delivery_refresh.pot
odoo/addons/stock_warehouse_flow_delivery_refresh/models/__init__.py
odoo/addons/stock_warehouse_flow_delivery_refresh/models/stock_move.py
odoo/addons/stock_warehouse_flow_delivery_refresh/models/stock_picking.py
odoo/addons/stock_warehouse_flow_delivery_refresh/readme/CONTRIBUTORS.rst
odoo/addons/stock_warehouse_flow_delivery_refresh/readme/DESCRIPTION.rst
odoo/addons/stock_warehouse_flow_delivery_refresh/static/description/icon.png
odoo/addons/stock_warehouse_flow_delivery_refresh/static/description/index.html
odoo/addons/stock_warehouse_flow_delivery_refresh/tests/__init__.py
odoo/addons/stock_warehouse_flow_delivery_refresh/tests/test_reapply_flow.py
odoo_addon_stock_warehouse_flow_delivery_refresh-16.0.1.0.0.4.dist-info/METADATA
odoo_addon_stock_warehouse_flow_delivery_refresh-16.0.1.0.0.4.dist-info/WHEEL
odoo_addon_stock_warehouse_flow_delivery_refresh-16.0.1.0.0.4.dist-info/top_level.txt
odoo_addon_stock_warehouse_flow_delivery_refresh-16.0.1.0.0.4.dist-info/RECORD
